nahiarhdNLP/__init__.py
nahiarhdNLP/datasets/__init__.py
nahiarhdNLP/datasets/emoji.csv
nahiarhdNLP/datasets/kamus.txt
nahiarhdNLP/datasets/kata_dasar_kbbi.csv
nahiarhdNLP/datasets/loaders.py
nahiarhdNLP/datasets/slang.csv
nahiarhdNLP/datasets/stop_word.csv
nahiarhdNLP/datasets/wordlist.json
nahiarhdNLP/preprocessing/__init__.py
nahiarhdNLP/preprocessing/main.py
nahiarhdNLP/preprocessing/cleaning/__init__.py
nahiarhdNLP/preprocessing/cleaning/text_cleaner.py
nahiarhdNLP/preprocessing/cleaning/text_cleaner_word.py
nahiarhdNLP/preprocessing/cleaning/text_replace.py
nahiarhdNLP/preprocessing/linguistic/__init__.py
nahiarhdNLP/preprocessing/linguistic/stemmer.py
nahiarhdNLP/preprocessing/linguistic/stopword.py
nahiarhdNLP/preprocessing/normalization/__init__.py
nahiarhdNLP/preprocessing/normalization/emoji.py
nahiarhdNLP/preprocessing/normalization/spell_corrector.py
nahiarhdNLP/preprocessing/tokenization/__init__.py
nahiarhdNLP/preprocessing/tokenization/tokenizer.py
nahiarhdNLP/tests/demo_features.py
nahiarhdnlp-1.5.3.dist-info/licenses/LICENSE
nahiarhdnlp-1.5.3.dist-info/METADATA
nahiarhdnlp-1.5.3.dist-info/WHEEL
nahiarhdnlp-1.5.3.dist-info/top_level.txt
nahiarhdnlp-1.5.3.dist-info/RECORD
